[
    {
        "name": "associate_id",
        "type": "STRING",
        "mode": "REQUIRED",
        "description": "Unique identifier for the customer."
    },
    {
        "name": "name",
        "type": "STRING",
        "mode": "REQUIRED",
        "description": "Name of customer"
    },
    {
        "name": "last_name",
        "type": "STRING",
        "mode": "REQUIRED",
        "description": "Last name of the customer"
    },
    {
        "name": "cpf",
        "type": "STRING",
        "mode": "REQUIRED",
        "description": "Unique identifier for the customer."
    },
    {
        "name": "email",
        "type": "STRING",
        "mode": "REQUIRED",
        "description": "Email address of the customer."
    },
    {
        "name": "phone",
        "type": "STRING",
        "mode": "REQUIRED",
        "description": "Phone number of the customer."
    },
    {
        "name": "birth_date",
        "type": "DATE",
        "mode": "REQUIRED",
        "description": "Date of birth of the customer."
    },
    {
        "name": "created_at",
        "type": "TIMESTAMP",
        "mode": "REQUIRED",
        "description": "Timestamp when the customer was created."
    },
    {
        "name": "updated_at",
        "type": "TIMESTAMP",
        "mode": "NULLABLE",
        "description": "Timestamp when the customer was last updated."
    },
    {
        "name": "deleted_at",
        "type": "TIMESTAMP",
        "mode": "NULLABLE",
        "description": "Timestamp when the card was deleted."
    }
]